fastdata/__init__.py
fastdata/_modidx.py
fastdata/core.py
python_fastdata-0.0.4.dist-info/LICENSE
python_fastdata-0.0.4.dist-info/METADATA
python_fastdata-0.0.4.dist-info/WHEEL
python_fastdata-0.0.4.dist-info/entry_points.txt
python_fastdata-0.0.4.dist-info/top_level.txt
python_fastdata-0.0.4.dist-info/RECORD
