Metadata-Version: 2.1
Name: python-fastdata
Version: 0.0.4
Summary: Easiest and fastest way to 1B synthetic tokens
Home-page: https://github.com/AnswerDotAI/fastdata
Author: ncoop57
Author-email: nc@answer.ai
License: Apache Software License 2.0
Keywords: nbdev jupyter notebook python
Classifier: Development Status :: 4 - Beta
Classifier: Intended Audience :: Developers
Classifier: Natural Language :: English
Classifier: Programming Language :: Python :: 3.9
Classifier: Programming Language :: Python :: 3.10
Classifier: Programming Language :: Python :: 3.11
Classifier: Programming Language :: Python :: 3.12
Classifier: License :: OSI Approved :: Apache Software License
Requires-Python: >=3.9
License-File: LICENSE
Requires-Dist: claudette
Requires-Dist: fastcore
Requires-Dist: ratelimit
Requires-Dist: tqdm
Requires-Dist: huggingface-hub
Provides-Extra: dev
Requires-Dist: black; extra == "dev"
Requires-Dist: datasets; extra == "dev"
Requires-Dist: ipykernel; extra == "dev"
Requires-Dist: nbdev; extra == "dev"
